src/Text_Labling_EN.py
src/__init__.py
text_labling_en-0.0.7.dist-info/METADATA
text_labling_en-0.0.7.dist-info/WHEEL
text_labling_en-0.0.7.dist-info/licenses/LICENSE
text_labling_en-0.0.7.dist-info/RECORD
