Metadata-Version: 2.1
Name: Text_Labling_EN
Version: 0.0.7
Summary: Auto labeling English text package
Author-email: Hisham Altayieb <20hishamibrahim@gmail.com>
License: MIT License
License-File: LICENSE
Classifier: License :: OSI Approved :: MIT License
Classifier: Operating System :: OS Independent
Classifier: Programming Language :: Python :: 3
Requires-Python: >=3.7
Requires-Dist: matplotlib
Requires-Dist: nltk
Requires-Dist: numpy
Requires-Dist: pandas
Requires-Dist: transformers
Requires-Dist: wordcloud
